changelog_checker/__init__.py
changelog_checker/cli.py
changelog_checker/core.py
changelog_checker/models.py
changelog_checker/py.typed
changelog_checker/utils.py
changelog_checker/version.py
changelog_checker/data/reserved-names.json
changelog_checker/output/__init__.py
changelog_checker/output/html_formatter.py
changelog_checker/output/rich_formatter.py
changelog_checker/parsers/__init__.py
changelog_checker/parsers/base.py
changelog_checker/parsers/pip_parser.py
changelog_checker/parsers/uv_parser.py
changelog_checker/research/__init__.py
changelog_checker/research/changelog_finder.py
changelog_checker/research/package_finder.py
changelog_checker-0.3.0.dist-info/METADATA
changelog_checker-0.3.0.dist-info/WHEEL
changelog_checker-0.3.0.dist-info/entry_points.txt
changelog_checker-0.3.0.dist-info/licenses/LICENSE
changelog_checker-0.3.0.dist-info/RECORD
