Metadata-Version: 2.4
Name: changelog-checker
Version: 0.3.0
Summary: A tool for analyzing dependency updates and their changelogs.
Project-URL: Homepage, https://github.com/MrNaif2018/changelog-checker
Project-URL: Source, https://github.com/MrNaif2018/changelog-checker
Project-URL: Changelog, https://github.com/MrNaif2018/changelog-checker/blob/master/CHANGELOG.md
Author-email: MrNaif2018 <chuff184@gmail.com>
License-Expression: MIT
License-File: LICENSE
Keywords: analysis,changelog,checker,dependency,update
Classifier: Development Status :: 4 - Beta
Classifier: Intended Audience :: Developers
Classifier: License :: OSI Approved :: MIT License
Classifier: Programming Language :: Python :: 3
Classifier: Programming Language :: Python :: 3.11
Classifier: Programming Language :: Python :: 3.12
Classifier: Programming Language :: Python :: 3.13
Classifier: Programming Language :: Python :: 3.14
Classifier: Topic :: Software Development :: Quality Assurance
Requires-Python: >=3.11
Requires-Dist: click>=8.2.1
Requires-Dist: distlib>=0.3.9
Requires-Dist: googlesearch-python>=1.3.0
Requires-Dist: requests>=2.32.4
Requires-Dist: rich>=14.0.0
Provides-Extra: beautiful-html
Requires-Dist: docutils>=0.21.2; extra == 'beautiful-html'
Requires-Dist: markdown>=3.8.2; extra == 'beautiful-html'
Provides-Extra: rst
Requires-Dist: rich-rst>=1.3.1; extra == 'rst'
